cli.py
DAG_yml_file_generator-1.0.1.dist-info/LICENSE
DAG_yml_file_generator-1.0.1.dist-info/METADATA
DAG_yml_file_generator-1.0.1.dist-info/WHEEL
DAG_yml_file_generator-1.0.1.dist-info/entry_points.txt
DAG_yml_file_generator-1.0.1.dist-info/top_level.txt
DAG_yml_file_generator-1.0.1.dist-info/RECORD
