Metadata-Version: 2.1
Name: DAG-yml-file-generator
Version: 1.0.1
Summary: tool to create .yml file for DAG
Author-email: name <name@email.co.za>
Classifier: Programming Language :: Python :: 3
Classifier: Operating System :: OS Independent
Requires-Python: >=3.11
License-File: LICENSE
